Metadata-Version: 2.1
Name: newtonEQ
Version: 0.0.7
Summary: A library of useful college physics formulas
Home-page: https://github.com/simonvaradaraj/newtonEQLib
Author: Simon Varadaraj
Author-email: s.varadaraj03@gmail.com
License: MIT
Keywords: physics,college,science
Platform: UNKNOWN
Classifier: Development Status :: 5 - Production/Stable
Classifier: Intended Audience :: Education
Classifier: Operating System :: Microsoft :: Windows :: Windows 10
Classifier: License :: OSI Approved :: MIT License
Classifier: Programming Language :: Python :: 3
License-File: LICENCE.txt
